materl/__init__.py
materl/agents.py
materl/algorithm.py
materl/compiler.py
materl/graph.py
materl/logging.py
materl/ops.py
materl-0.1.1.dist-info/licenses/LICENSE
materl-0.1.1.dist-info/METADATA
materl-0.1.1.dist-info/WHEEL
materl-0.1.1.dist-info/top_level.txt
materl-0.1.1.dist-info/RECORD
