Metadata-Version: 2.4
Name: materl
Version: 0.1.1
Summary: Add your description here
Author-email: Teïlo Millet <teilomillet@gmail.com>
Requires-Python: >=3.10
License-File: LICENSE
Requires-Dist: modular>=25.3.0
Requires-Dist: torch>=2.5.0
Requires-Dist: transformers>=4.52.3
Requires-Dist: trl>=0.17.0
Requires-Dist: wandb>=0.20.1
Dynamic: license-file
